flake8_spellcheck/__init__.py
flake8_spellcheck/django.txt
flake8_spellcheck/en_US.txt
flake8_spellcheck/pandas.txt
flake8_spellcheck/python.txt
flake8_spellcheck/technical.txt
flake8_spellcheck/version.py
flake8_spellcheck-0.26.0.dist-info/LICENSE
flake8_spellcheck-0.26.0.dist-info/METADATA
flake8_spellcheck-0.26.0.dist-info/WHEEL
flake8_spellcheck-0.26.0.dist-info/entry_points.txt
flake8_spellcheck-0.26.0.dist-info/top_level.txt
flake8_spellcheck-0.26.0.dist-info/RECORD
