Metadata-Version: 2.1
Name: flake8-spellcheck
Version: 0.26.0
Summary: Spellcheck variables, comments and docstrings
Home-page: https://github.com/MichaelAquilina/flake8-spellcheck
Author: Michael Aquilina
Author-email: michaelaquilina@gmail.com
License: MIT
Platform: UNKNOWN
Classifier: Framework :: Flake8
Classifier: Environment :: Console
Classifier: Intended Audience :: Developers
Classifier: License :: OSI Approved :: MIT License
Classifier: Programming Language :: Python
Classifier: Programming Language :: Python :: 3
Classifier: Topic :: Software Development :: Libraries :: Python Modules
Classifier: Topic :: Software Development :: Quality Assurance
License-File: LICENSE
Requires-Dist: flake8 (>3.0.0)
